hostopen/__init__.py
hostopen/arg_handler.py
hostopen/client.py
hostopen/server.py
hostopen/utils.py
hostopen-0.1.1.dist-info/DESCRIPTION.rst
hostopen-0.1.1.dist-info/METADATA
hostopen-0.1.1.dist-info/RECORD
hostopen-0.1.1.dist-info/WHEEL
hostopen-0.1.1.dist-info/entry_points.txt
hostopen-0.1.1.dist-info/metadata.json
hostopen-0.1.1.dist-info/top_level.txt
