Metadata-Version: 2.0
Name: hostopen
Version: 0.1.1
Summary: Open files/directories in a vagrant synced folder on the host
Home-page: https://github.com/jaketreacher/hostopen
Author: Jake Treacher
Author-email: git@jaketreacher.com
License: MIT
Platform: UNKNOWN
Classifier: Development Status :: 3 - Alpha
Classifier: Environment :: Console
Classifier: Intended Audience :: Developers
Classifier: License :: OSI Approved :: MIT License
Classifier: Programming Language :: Python :: 3
Classifier: Programming Language :: Python :: 3.5
Classifier: Programming Language :: Python :: 3.6
Classifier: Programming Language :: Python :: 3 :: Only
Classifier: Topic :: Utilities
Requires-Python: >=3
